LICENSE
hardwario/chester/__init__.py
hardwario/chester/app.py
hardwario/chester/build.py
hardwario/chester/cli/__init__.py
hardwario/chester/cli/app.py
hardwario/chester/cli/lte.py
hardwario/chester/console.py
hardwario/chester/firmwareapi.py
hardwario/chester/nrfjprog.py
hardwario/chester/pib.py
hardwario/chester/utils.py
hardwario_chester-1.28.2.dist-info/LICENSE
hardwario_chester-1.28.2.dist-info/METADATA
hardwario_chester-1.28.2.dist-info/WHEEL
hardwario_chester-1.28.2.dist-info/entry_points.txt
hardwario_chester-1.28.2.dist-info/RECORD
