Metadata-Version: 2.1
Name: hardwario-chester
Version: 1.28.2
Summary: HARDWARIO CHESTER
Home-page: https://github.com/hardwario/py-hardwario-chester
License: MIT
Author: Karel Blavka
Author-email: karel.blavka@hardwario.com
Requires-Python: >=3.8,<4
Classifier: Development Status :: 5 - Production/Stable
Classifier: Environment :: Console
Classifier: License :: OSI Approved :: MIT License
Classifier: Operating System :: OS Independent
Classifier: Programming Language :: Python :: 3
Classifier: Programming Language :: Python :: 3.8
Classifier: Programming Language :: Python :: 3.9
Classifier: Programming Language :: Python :: 3.10
Classifier: Programming Language :: Python :: 3.11
Classifier: Programming Language :: Python :: 3.12
Classifier: Programming Language :: Python :: 3.7
Classifier: Topic :: Software Development :: Libraries :: Python Modules
Classifier: Topic :: Utilities
Requires-Dist: Pygments (>=2.18.0,<3.0.0)
Requires-Dist: click (>=8.1.3,<9.0.0)
Requires-Dist: docker (>=7.1.0,<8.0.0)
Requires-Dist: hardwario-common (==1.9.0)
Requires-Dist: loguru (>=0.7.2,<0.8.0)
Requires-Dist: prompt-toolkit (==3.0.31)
Requires-Dist: pylink-square (==1.2.0)
Requires-Dist: pynrfjprog (==10.17.3)
Requires-Dist: pyperclip (>=1.8.2,<2.0.0)
Requires-Dist: requests (>=2.32.3,<3.0.0)
Requires-Dist: watchdog (>=4.0.1,<5.0.0)
Project-URL: Repository, https://github.com/hardwario/py-hardwario-chester
